smartystreets/__init__.py
smartystreets/client.py
smartystreets/data.py
smartystreets/decorators.py
smartystreets/exceptions.py
smartystreets_py-2.0.2.dist-info/METADATA
smartystreets_py-2.0.2.dist-info/WHEEL
smartystreets_py-2.0.2.dist-info/licenses/AUTHORS.rst
smartystreets_py-2.0.2.dist-info/licenses/LICENSE
smartystreets_py-2.0.2.dist-info/RECORD
