Metadata-Version: 2.4
Name: smartystreets.py
Version: 2.0.2
Summary: A simple client for the SmartyStreets address validation and geolocation API
Project-URL: Homepage, https://github.com/bennylope/smartystreets.py
Author-email: Ben Lopatin <ben@benlopatin.com>
License: BSD
License-File: AUTHORS.rst
License-File: LICENSE
Keywords: smarty,smartystreets
Classifier: Development Status :: 5 - Production/Stable
Classifier: Intended Audience :: Developers
Classifier: License :: OSI Approved :: BSD License
Classifier: Natural Language :: English
Classifier: Programming Language :: Python :: 3
Classifier: Programming Language :: Python :: 3.9
Classifier: Programming Language :: Python :: 3.10
Classifier: Programming Language :: Python :: 3.11
Classifier: Programming Language :: Python :: 3.12
Classifier: Programming Language :: Python :: 3.13
Classifier: Topic :: Internet :: WWW/HTTP
Requires-Python: >=3.9
Requires-Dist: httpx>=0.19.0
Provides-Extra: dev
Requires-Dist: pre-commit==4.0.1; extra == 'dev'
Provides-Extra: test
Requires-Dist: pytest-cov==6.0.0; extra == 'test'
Requires-Dist: pytest-mock==3.14.0; extra == 'test'
Requires-Dist: pytest-socket==0.7.0; extra == 'test'
Requires-Dist: pytest==8.3.4; extra == 'test'
Requires-Dist: respx==0.22.0; extra == 'test'
